agent/__init__.py
agent/clickhouse_agent.py
agent/config.py
agent/default_instruction.py
agent/history_processor.py
agent/py.typed
clickhouse_mcp_agent-0.8.0.dist-info/licenses/LICENSE
clickhouse_mcp_agent-0.8.0.dist-info/METADATA
clickhouse_mcp_agent-0.8.0.dist-info/WHEEL
clickhouse_mcp_agent-0.8.0.dist-info/top_level.txt
clickhouse_mcp_agent-0.8.0.dist-info/RECORD
