Metadata-Version: 2.4
Name: clickhouse-mcp-agent
Version: 0.8.0
Summary: AI agent for ClickHouse database analysis via MCP
Author-email: Altuğ Ceylan <altug.ceylan.yes@gmail.com>
License: MIT
Project-URL: Homepage, https://github.com/AranNomante/clickhousemcp
Project-URL: Repository, https://github.com/AranNomante/clickhousemcp
Project-URL: Issues, https://github.com/AranNomante/clickhousemcp/issues
Keywords: clickhouse,mcp,ai,database,analysis
Classifier: Development Status :: 5 - Production/Stable
Classifier: Intended Audience :: Developers
Classifier: License :: OSI Approved :: MIT License
Classifier: Operating System :: OS Independent
Classifier: Programming Language :: Python :: 3
Classifier: Programming Language :: Python :: 3.10
Classifier: Programming Language :: Python :: 3.11
Classifier: Programming Language :: Python :: 3.12
Classifier: Topic :: Database
Classifier: Topic :: Scientific/Engineering :: Artificial Intelligence
Requires-Python: >=3.10
License-File: LICENSE
Requires-Dist: pydantic-ai-slim[anthropic,cohere,google,groq,mcp,mistral,openai,vertexai]
Requires-Dist: mcp-clickhouse
Requires-Dist: python-dotenv
Requires-Dist: uv
Provides-Extra: dev
Requires-Dist: pytest; extra == "dev"
Requires-Dist: pytest-asyncio; extra == "dev"
Requires-Dist: black; extra == "dev"
Requires-Dist: isort; extra == "dev"
Requires-Dist: mypy; extra == "dev"
Requires-Dist: flake8; extra == "dev"
Requires-Dist: types-cachetools; extra == "dev"
Provides-Extra: examples
Requires-Dist: jupyter; extra == "examples"
Requires-Dist: ipython; extra == "examples"
Dynamic: license-file
